pylint_print/__init__.py
pylint_print/__version__.py
pylint_print/pylint_print.py
pylint_print-1.0.1.dist-info/METADATA
pylint_print-1.0.1.dist-info/WHEEL
pylint_print-1.0.1.dist-info/top_level.txt
pylint_print-1.0.1.dist-info/RECORD
