Metadata-Version: 2.1
Name: pylint-print
Version: 1.0.1
Summary: Print function checker for PyLint
Home-page: https://gitlab.com/nwmitchell/pylint-print
Author: Nick Mitchell
Author-email: nmitchell@nvidia.com
License: GPLv2
Classifier: Programming Language :: Python :: 3
Classifier: License :: OSI Approved :: GNU General Public License v2 (GPLv2)
Classifier: Operating System :: OS Independent
Requires-Python: >=3.6
Requires-Dist: pylint
